{
 "cells": [
  {
   "cell_type": "code",
   "execution_count": 1,
   "metadata": {},
   "outputs": [],
   "source": [
    "def selection_sort(elements):\n",
    "    results = []\n",
    "    \n",
    "    \n",
    "    while elements:\n",
    "        min_num = float('inf')\n",
    "        min_index = -1\n",
    "        \n",
    "        for i in range(len(elements)):\n",
    "            if min_num > elements[i]:\n",
    "                min_num = elements[i]\n",
    "                min_index = i\n",
    "                \n",
    "#@        ic(min_index)\n",
    "#        ic(len(elements))\n",
    "        results.append(elements.pop(min_index))\n",
    "    \n",
    "    return results"
   ]
  },
  {
   "cell_type": "code",
   "execution_count": 2,
   "metadata": {},
   "outputs": [],
   "source": [
    "def merge_sort(elements):\n",
    "#    ic(elements)\n",
    "    if len(elements) <= 1: return elements\n",
    "    \n",
    "    left_result = merge_sort(elements[:len(elements)//2])\n",
    "    right_result = merge_sort(elements[len(elements)//2:])\n",
    "    \n",
    "    results = []\n",
    "    \n",
    "    i, j = 0, 0\n",
    "    \n",
    "    while i < len(left_result) and j < len(right_result):\n",
    "        if left_result[i] < right_result[j]:\n",
    "            results.append(left_result[i])\n",
    "            i += 1\n",
    "        else:\n",
    "            results.append(right_result[j])\n",
    "            j += 1\n",
    "#     ic(i, j)\n",
    "#     ic(results)\n",
    "#     ic(left_result)\n",
    "    if i == len(left_result):  # left is reached the end\n",
    "        results += right_result[j:]\n",
    "    else:\n",
    "        results += left_result[i:]\n",
    "    \n",
    "    return results"
   ]
  },
  {
   "cell_type": "code",
   "execution_count": 4,
   "metadata": {},
   "outputs": [],
   "source": [
    "import dis"
   ]
  },
  {
   "cell_type": "code",
   "execution_count": 5,
   "metadata": {},
   "outputs": [
    {
     "name": "stdout",
     "output_type": "stream",
     "text": [
      "  2           0 BUILD_LIST               0\n",
      "              2 STORE_FAST               1 (results)\n",
      "\n",
      "  5           4 SETUP_LOOP              82 (to 88)\n",
      "        >>    6 LOAD_FAST                0 (elements)\n",
      "              8 POP_JUMP_IF_FALSE       86\n",
      "\n",
      "  6          10 LOAD_GLOBAL              0 (float)\n",
      "             12 LOAD_CONST               1 ('inf')\n",
      "             14 CALL_FUNCTION            1\n",
      "             16 STORE_FAST               2 (min_num)\n",
      "\n",
      "  7          18 LOAD_CONST               2 (-1)\n",
      "             20 STORE_FAST               3 (min_index)\n",
      "\n",
      "  9          22 SETUP_LOOP              44 (to 68)\n",
      "             24 LOAD_GLOBAL              1 (range)\n",
      "             26 LOAD_GLOBAL              2 (len)\n",
      "             28 LOAD_FAST                0 (elements)\n",
      "             30 CALL_FUNCTION            1\n",
      "             32 CALL_FUNCTION            1\n",
      "             34 GET_ITER\n",
      "        >>   36 FOR_ITER                28 (to 66)\n",
      "             38 STORE_FAST               4 (i)\n",
      "\n",
      " 10          40 LOAD_FAST                2 (min_num)\n",
      "             42 LOAD_FAST                0 (elements)\n",
      "             44 LOAD_FAST                4 (i)\n",
      "             46 BINARY_SUBSCR\n",
      "             48 COMPARE_OP               4 (>)\n",
      "             50 POP_JUMP_IF_FALSE       36\n",
      "\n",
      " 11          52 LOAD_FAST                0 (elements)\n",
      "             54 LOAD_FAST                4 (i)\n",
      "             56 BINARY_SUBSCR\n",
      "             58 STORE_FAST               2 (min_num)\n",
      "\n",
      " 12          60 LOAD_FAST                4 (i)\n",
      "             62 STORE_FAST               3 (min_index)\n",
      "             64 JUMP_ABSOLUTE           36\n",
      "        >>   66 POP_BLOCK\n",
      "\n",
      " 16     >>   68 LOAD_FAST                1 (results)\n",
      "             70 LOAD_METHOD              3 (append)\n",
      "             72 LOAD_FAST                0 (elements)\n",
      "             74 LOAD_METHOD              4 (pop)\n",
      "             76 LOAD_FAST                3 (min_index)\n",
      "             78 CALL_METHOD              1\n",
      "             80 CALL_METHOD              1\n",
      "             82 POP_TOP\n",
      "             84 JUMP_ABSOLUTE            6\n",
      "        >>   86 POP_BLOCK\n",
      "\n",
      " 18     >>   88 LOAD_FAST                1 (results)\n",
      "             90 RETURN_VALUE\n"
     ]
    }
   ],
   "source": [
    "dis.dis(selection_sort)"
   ]
  },
  {
   "cell_type": "code",
   "execution_count": 6,
   "metadata": {},
   "outputs": [
    {
     "name": "stdout",
     "output_type": "stream",
     "text": [
      "  3           0 LOAD_GLOBAL              0 (len)\n",
      "              2 LOAD_FAST                0 (elements)\n",
      "              4 CALL_FUNCTION            1\n",
      "              6 LOAD_CONST               1 (1)\n",
      "              8 COMPARE_OP               1 (<=)\n",
      "             10 POP_JUMP_IF_FALSE       16\n",
      "             12 LOAD_FAST                0 (elements)\n",
      "             14 RETURN_VALUE\n",
      "\n",
      "  5     >>   16 LOAD_GLOBAL              1 (merge_sort)\n",
      "             18 LOAD_FAST                0 (elements)\n",
      "             20 LOAD_CONST               0 (None)\n",
      "             22 LOAD_GLOBAL              0 (len)\n",
      "             24 LOAD_FAST                0 (elements)\n",
      "             26 CALL_FUNCTION            1\n",
      "             28 LOAD_CONST               2 (2)\n",
      "             30 BINARY_FLOOR_DIVIDE\n",
      "             32 BUILD_SLICE              2\n",
      "             34 BINARY_SUBSCR\n",
      "             36 CALL_FUNCTION            1\n",
      "             38 STORE_FAST               1 (left_result)\n",
      "\n",
      "  6          40 LOAD_GLOBAL              1 (merge_sort)\n",
      "             42 LOAD_FAST                0 (elements)\n",
      "             44 LOAD_GLOBAL              0 (len)\n",
      "             46 LOAD_FAST                0 (elements)\n",
      "             48 CALL_FUNCTION            1\n",
      "             50 LOAD_CONST               2 (2)\n",
      "             52 BINARY_FLOOR_DIVIDE\n",
      "             54 LOAD_CONST               0 (None)\n",
      "             56 BUILD_SLICE              2\n",
      "             58 BINARY_SUBSCR\n",
      "             60 CALL_FUNCTION            1\n",
      "             62 STORE_FAST               2 (right_result)\n",
      "\n",
      "  8          64 BUILD_LIST               0\n",
      "             66 STORE_FAST               3 (results)\n",
      "\n",
      " 10          68 LOAD_CONST               3 ((0, 0))\n",
      "             70 UNPACK_SEQUENCE          2\n",
      "             72 STORE_FAST               4 (i)\n",
      "             74 STORE_FAST               5 (j)\n",
      "\n",
      " 12          76 SETUP_LOOP              90 (to 168)\n",
      "        >>   78 LOAD_FAST                4 (i)\n",
      "             80 LOAD_GLOBAL              0 (len)\n",
      "             82 LOAD_FAST                1 (left_result)\n",
      "             84 CALL_FUNCTION            1\n",
      "             86 COMPARE_OP               0 (<)\n",
      "             88 POP_JUMP_IF_FALSE      166\n",
      "             90 LOAD_FAST                5 (j)\n",
      "             92 LOAD_GLOBAL              0 (len)\n",
      "             94 LOAD_FAST                2 (right_result)\n",
      "             96 CALL_FUNCTION            1\n",
      "             98 COMPARE_OP               0 (<)\n",
      "            100 POP_JUMP_IF_FALSE      166\n",
      "\n",
      " 13         102 LOAD_FAST                1 (left_result)\n",
      "            104 LOAD_FAST                4 (i)\n",
      "            106 BINARY_SUBSCR\n",
      "            108 LOAD_FAST                2 (right_result)\n",
      "            110 LOAD_FAST                5 (j)\n",
      "            112 BINARY_SUBSCR\n",
      "            114 COMPARE_OP               0 (<)\n",
      "            116 POP_JUMP_IF_FALSE      142\n",
      "\n",
      " 14         118 LOAD_FAST                3 (results)\n",
      "            120 LOAD_METHOD              2 (append)\n",
      "            122 LOAD_FAST                1 (left_result)\n",
      "            124 LOAD_FAST                4 (i)\n",
      "            126 BINARY_SUBSCR\n",
      "            128 CALL_METHOD              1\n",
      "            130 POP_TOP\n",
      "\n",
      " 15         132 LOAD_FAST                4 (i)\n",
      "            134 LOAD_CONST               1 (1)\n",
      "            136 INPLACE_ADD\n",
      "            138 STORE_FAST               4 (i)\n",
      "            140 JUMP_ABSOLUTE           78\n",
      "\n",
      " 17     >>  142 LOAD_FAST                3 (results)\n",
      "            144 LOAD_METHOD              2 (append)\n",
      "            146 LOAD_FAST                2 (right_result)\n",
      "            148 LOAD_FAST                5 (j)\n",
      "            150 BINARY_SUBSCR\n",
      "            152 CALL_METHOD              1\n",
      "            154 POP_TOP\n",
      "\n",
      " 18         156 LOAD_FAST                5 (j)\n",
      "            158 LOAD_CONST               1 (1)\n",
      "            160 INPLACE_ADD\n",
      "            162 STORE_FAST               5 (j)\n",
      "            164 JUMP_ABSOLUTE           78\n",
      "        >>  166 POP_BLOCK\n",
      "\n",
      " 22     >>  168 LOAD_FAST                4 (i)\n",
      "            170 LOAD_GLOBAL              0 (len)\n",
      "            172 LOAD_FAST                1 (left_result)\n",
      "            174 CALL_FUNCTION            1\n",
      "            176 COMPARE_OP               2 (==)\n",
      "            178 POP_JUMP_IF_FALSE      198\n",
      "\n",
      " 23         180 LOAD_FAST                3 (results)\n",
      "            182 LOAD_FAST                2 (right_result)\n",
      "            184 LOAD_FAST                5 (j)\n",
      "            186 LOAD_CONST               0 (None)\n",
      "            188 BUILD_SLICE              2\n",
      "            190 BINARY_SUBSCR\n",
      "            192 INPLACE_ADD\n",
      "            194 STORE_FAST               3 (results)\n",
      "            196 JUMP_FORWARD            16 (to 214)\n",
      "\n",
      " 25     >>  198 LOAD_FAST                3 (results)\n",
      "            200 LOAD_FAST                1 (left_result)\n",
      "            202 LOAD_FAST                4 (i)\n",
      "            204 LOAD_CONST               0 (None)\n",
      "            206 BUILD_SLICE              2\n",
      "            208 BINARY_SUBSCR\n",
      "            210 INPLACE_ADD\n",
      "            212 STORE_FAST               3 (results)\n",
      "\n",
      " 27     >>  214 LOAD_FAST                3 (results)\n",
      "            216 RETURN_VALUE\n"
     ]
    }
   ],
   "source": [
    "dis.dis(merge_sort)"
   ]
  },
  {
   "cell_type": "code",
   "execution_count": 8,
   "metadata": {},
   "outputs": [
    {
     "name": "stdout",
     "output_type": "stream",
     "text": [
      "  1           0 LOAD_FAST                0 (x)\n",
      "              2 LOAD_CONST               1 (4)\n",
      "              4 BINARY_POWER\n",
      "              6 RETURN_VALUE\n"
     ]
    }
   ],
   "source": [
    "dis.dis(lambda x: x ** 4)"
   ]
  },
  {
   "cell_type": "code",
   "execution_count": 9,
   "metadata": {},
   "outputs": [
    {
     "name": "stdout",
     "output_type": "stream",
     "text": [
      "  1           0 LOAD_CONST               1 ('this is ')\n",
      "              2 LOAD_FAST                0 (x)\n",
      "              4 BINARY_ADD\n",
      "              6 RETURN_VALUE\n"
     ]
    }
   ],
   "source": [
    "dis.dis(lambda x: 'this is ' + x)"
   ]
  }
 ],
 "metadata": {
  "kernelspec": {
   "display_name": "Python 3",
   "language": "python",
   "name": "python3"
  },
  "language_info": {
   "codemirror_mode": {
    "name": "ipython",
    "version": 3
   },
   "file_extension": ".py",
   "mimetype": "text/x-python",
   "name": "python",
   "nbconvert_exporter": "python",
   "pygments_lexer": "ipython3",
   "version": "3.7.3"
  }
 },
 "nbformat": 4,
 "nbformat_minor": 2
}
